kinneyotpgui/__init__.py
kinneyotpgui/form.py
kinneyotpgui/main.py
kinneyotpgui-0.0.7.dist-info/METADATA
kinneyotpgui-0.0.7.dist-info/WHEEL
kinneyotpgui-0.0.7.dist-info/entry_points.txt
kinneyotpgui-0.0.7.dist-info/top_level.txt
kinneyotpgui-0.0.7.dist-info/RECORD
