Metadata-Version: 2.1
Name: kinneyotpgui
Version: 0.0.7
Summary: Graphical user interface for one time pad
Author: Mike Kinney
Author-email: mike.kinney@gmail.com
Classifier: Development Status :: 4 - Beta
Classifier: Programming Language :: Python :: 3.10
Requires-Python: >=3.6
Requires-Dist: pyside6
Requires-Dist: kinneyotp
